{
    "headerWidth": 4,
    "headers": [
        {
            "column": "Data",
            "hidden": false,
            "meta": true,
            "name": "dx",
            "type": "java.lang.String",
            "valueType": "TEXT"
        },
        {
            "column": "Period",
            "hidden": false,
            "meta": true,
            "name": "pe",
            "type": "java.lang.String",
            "valueType": "TEXT"
        },
        {
            "column": "Organisation unit",
            "hidden": false,
            "meta": true,
            "name": "ou",
            "type": "java.lang.String",
            "valueType": "TEXT"
        },
        {
            "column": "Value",
            "hidden": false,
            "meta": false,
            "name": "value",
            "type": "java.lang.Double",
            "valueType": "NUMBER"
        }
    ],
    "height": 707,
    "metaData": {
        "dimensions": {
            "co": [
                "YgSzuXIfed6",
                "EW1nknsma47"
            ],
            "dx": [
                "wryMP8p8k1C"
            ],
            "ou": [
                "W6sNfkJcXGC",
                "YvLOmtTQD6b",
                "XKGgynPS1WZ",
                "rO2RVJWHpCe",
                "FRmrFTE63D0",
                "MBZYTqkEgwf",
                "hdeC7uX9Cko",
                "RdNV4tTRNEo",
                "VWGSudnonm5",
                "quFXhkOJGB4",
                "vBWtCmNNnCG",
                "c4HrGRJoarj",
                "pFCZqWnXtoU",
                "TOgZ99Jv0bN",
                "dOhqCNenSjS",
                "sv6c7CpPcrc",
                "hRQsZhmvqgS",
                "K27JzTKmBKh"
            ],
            "pe": [
                "2023W16",
                "2023W17",
                "2023W18",
                "2023W19",
                "2023W20",
                "2023W21",
                "2023W22",
                "2023W23",
                "2023W24",
                "2023W25",
                "2023W26",
                "2023W27",
                "2023W28",
                "2023W29",
                "2023W30",
                "2023W31",
                "2023W32",
                "2023W33",
                "2023W34",
                "2023W35",
                "2023W36",
                "2023W37",
                "2023W38",
                "2023W39",
                "2023W40",
                "2023W41",
                "2023W42",
                "2023W43",
                "2023W44",
                "2023W45",
                "2023W46",
                "2023W47",
                "2023W48",
                "2023W49",
                "2023W50",
                "2023W51",
                "2023W52",
                "2024W1",
                "2024W2",
                "2024W3",
                "2024W4",
                "2024W5",
                "2024W6",
                "2024W7",
                "2024W8",
                "2024W9",
                "2024W10",
                "2024W11",
                "2024W12",
                "2024W13",
                "2024W14",
                "2024W15"
            ]
        },
        "items": {
            "2023W16": {
                "name": "Week 16 2023-04-17 - 2023-04-23"
            },
            "2023W17": {
                "name": "Week 17 2023-04-24 - 2023-04-30"
            },
            "2023W18": {
                "name": "Week 18 2023-05-01 - 2023-05-07"
            },
            "2023W19": {
                "name": "Week 19 2023-05-08 - 2023-05-14"
            },
            "2023W20": {
                "name": "Week 20 2023-05-15 - 2023-05-21"
            },
            "2023W21": {
                "name": "Week 21 2023-05-22 - 2023-05-28"
            },
            "2023W22": {
                "name": "Week 22 2023-05-29 - 2023-06-04"
            },
            "2023W23": {
                "name": "Week 23 2023-06-05 - 2023-06-11"
            },
            "2023W24": {
                "name": "Week 24 2023-06-12 - 2023-06-18"
            },
            "2023W25": {
                "name": "Week 25 2023-06-19 - 2023-06-25"
            },
            "2023W26": {
                "name": "Week 26 2023-06-26 - 2023-07-02"
            },
            "2023W27": {
                "name": "Week 27 2023-07-03 - 2023-07-09"
            },
            "2023W28": {
                "name": "Week 28 2023-07-10 - 2023-07-16"
            },
            "2023W29": {
                "name": "Week 29 2023-07-17 - 2023-07-23"
            },
            "2023W30": {
                "name": "Week 30 2023-07-24 - 2023-07-30"
            },
            "2023W31": {
                "name": "Week 31 2023-07-31 - 2023-08-06"
            },
            "2023W32": {
                "name": "Week 32 2023-08-07 - 2023-08-13"
            },
            "2023W33": {
                "name": "Week 33 2023-08-14 - 2023-08-20"
            },
            "2023W34": {
                "name": "Week 34 2023-08-21 - 2023-08-27"
            },
            "2023W35": {
                "name": "Week 35 2023-08-28 - 2023-09-03"
            },
            "2023W36": {
                "name": "Week 36 2023-09-04 - 2023-09-10"
            },
            "2023W37": {
                "name": "Week 37 2023-09-11 - 2023-09-17"
            },
            "2023W38": {
                "name": "Week 38 2023-09-18 - 2023-09-24"
            },
            "2023W39": {
                "name": "Week 39 2023-09-25 - 2023-10-01"
            },
            "2023W40": {
                "name": "Week 40 2023-10-02 - 2023-10-08"
            },
            "2023W41": {
                "name": "Week 41 2023-10-09 - 2023-10-15"
            },
            "2023W42": {
                "name": "Week 42 2023-10-16 - 2023-10-22"
            },
            "2023W43": {
                "name": "Week 43 2023-10-23 - 2023-10-29"
            },
            "2023W44": {
                "name": "Week 44 2023-10-30 - 2023-11-05"
            },
            "2023W45": {
                "name": "Week 45 2023-11-06 - 2023-11-12"
            },
            "2023W46": {
                "name": "Week 46 2023-11-13 - 2023-11-19"
            },
            "2023W47": {
                "name": "Week 47 2023-11-20 - 2023-11-26"
            },
            "2023W48": {
                "name": "Week 48 2023-11-27 - 2023-12-03"
            },
            "2023W49": {
                "name": "Week 49 2023-12-04 - 2023-12-10"
            },
            "2023W50": {
                "name": "Week 50 2023-12-11 - 2023-12-17"
            },
            "2023W51": {
                "name": "Week 51 2023-12-18 - 2023-12-24"
            },
            "2023W52": {
                "name": "Week 52 2023-12-25 - 2023-12-31"
            },
            "2024W1": {
                "name": "Week 1 2024-01-01 - 2024-01-07"
            },
            "2024W10": {
                "name": "Week 10 2024-03-04 - 2024-03-10"
            },
            "2024W11": {
                "name": "Week 11 2024-03-11 - 2024-03-17"
            },
            "2024W12": {
                "name": "Week 12 2024-03-18 - 2024-03-24"
            },
            "2024W13": {
                "name": "Week 13 2024-03-25 - 2024-03-31"
            },
            "2024W14": {
                "name": "Week 14 2024-04-01 - 2024-04-07"
            },
            "2024W15": {
                "name": "Week 15 2024-04-08 - 2024-04-14"
            },
            "2024W2": {
                "name": "Week 2 2024-01-08 - 2024-01-14"
            },
            "2024W3": {
                "name": "Week 3 2024-01-15 - 2024-01-21"
            },
            "2024W4": {
                "name": "Week 4 2024-01-22 - 2024-01-28"
            },
            "2024W5": {
                "name": "Week 5 2024-01-29 - 2024-02-04"
            },
            "2024W6": {
                "name": "Week 6 2024-02-05 - 2024-02-11"
            },
            "2024W7": {
                "name": "Week 7 2024-02-12 - 2024-02-18"
            },
            "2024W8": {
                "name": "Week 8 2024-02-19 - 2024-02-25"
            },
            "2024W9": {
                "name": "Week 9 2024-02-26 - 2024-03-03"
            },
            "EW1nknsma47": {
                "name": "5+ years"
            },
            "FRmrFTE63D0": {
                "name": "05 Bokeo"
            },
            "K27JzTKmBKh": {
                "name": "18 Xaisomboun"
            },
            "LAST_52_WEEKS": {
                "name": "Last 52 weeks"
            },
            "MBZYTqkEgwf": {
                "name": "06 Louangphabang"
            },
            "RdNV4tTRNEo": {
                "name": "08 Xainyabouli"
            },
            "TOgZ99Jv0bN": {
                "name": "14 Salavan"
            },
            "VWGSudnonm5": {
                "name": "09 Xiangkhouang"
            },
            "W6sNfkJcXGC": {
                "name": "01 Vientiane Capital"
            },
            "XKGgynPS1WZ": {
                "name": "03 Louangnamtha"
            },
            "YgSzuXIfed6": {
                "name": "0-4 years"
            },
            "YvLOmtTQD6b": {
                "name": "02 Phongsali"
            },
            "c4HrGRJoarj": {
                "name": "12 Khammouan"
            },
            "dOhqCNenSjS": {
                "name": "15 Xekong"
            },
            "dx": {
                "name": "Data"
            },
            "hRQsZhmvqgS": {
                "name": "17 Attapu"
            },
            "hdeC7uX9Cko": {
                "name": "07 Houaphan"
            },
            "ou": {
                "name": "Organisation unit"
            },
            "pFCZqWnXtoU": {
                "name": "13 Savannakhet"
            },
            "pe": {
                "name": "Period"
            },
            "qpXLDdXT3po": {
                "name": "Province",
                "uid": "qpXLDdXT3po"
            },
            "quFXhkOJGB4": {
                "name": "10 Vientiane"
            },
            "rO2RVJWHpCe": {
                "name": "04 Oudomxai"
            },
            "sv6c7CpPcrc": {
                "name": "16 Champasak"
            },
            "vBWtCmNNnCG": {
                "name": "11 Bolikhamxai"
            },
            "wryMP8p8k1C": {
                "name": "IDS - Dengue Fever (Suspected cases)"
            }
        }
    },
    "rowContext": {},
    "rows": [
        [
            "wryMP8p8k1C",
            "2023W25",
            "c4HrGRJoarj",
            "9"
        ],
        [
            "wryMP8p8k1C",
            "2024W8",
            "vBWtCmNNnCG",
            "57"
        ],
        [
            "wryMP8p8k1C",
            "2023W47",
            "YvLOmtTQD6b",
            "8"
        ],
        [
            "wryMP8p8k1C",
            "2023W49",
            "YvLOmtTQD6b",
            "8"
        ],
        [
            "wryMP8p8k1C",
            "2023W24",
            "c4HrGRJoarj",
            "4"
        ],
        [
            "wryMP8p8k1C",
            "2023W28",
            "c4HrGRJoarj",
            "13"
        ],
        [
            "wryMP8p8k1C",
            "2024W5",
            "vBWtCmNNnCG",
            "50"
        ],
        [
            "wryMP8p8k1C",
            "2024W9",
            "vBWtCmNNnCG",
            "44"
        ],
        [
            "wryMP8p8k1C",
            "2023W48",
            "YvLOmtTQD6b",
            "7"
        ],
        [
            "wryMP8p8k1C",
            "2023W21",
            "c4HrGRJoarj",
            "1"
        ],
        [
            "wryMP8p8k1C",
            "2023W29",
            "c4HrGRJoarj",
            "16"
        ],
        [
            "wryMP8p8k1C",
            "2024W4",
            "vBWtCmNNnCG",
            "42"
        ],
        [
            "wryMP8p8k1C",
            "2023W44",
            "VWGSudnonm5",
            "43"
        ],
        [
            "wryMP8p8k1C",
            "2023W45",
            "VWGSudnonm5",
            "42"
        ],
        [
            "wryMP8p8k1C",
            "2023W45",
            "YvLOmtTQD6b",
            "8"
        ],
        [
            "wryMP8p8k1C",
            "2023W23",
            "c4HrGRJoarj",
            "1"
        ],
        [
            "wryMP8p8k1C",
            "2024W2",
            "vBWtCmNNnCG",
            "33"
        ],
        [
            "wryMP8p8k1C",
            "2023W22",
            "c4HrGRJoarj",
            "9"
        ],
        [
            "wryMP8p8k1C",
            "2024W3",
            "vBWtCmNNnCG",
            "43"
        ],
        [
            "wryMP8p8k1C",
            "2023W46",
            "YvLOmtTQD6b",
            "11"
        ],
        [
            "wryMP8p8k1C",
            "2024W1",
            "vBWtCmNNnCG",
            "35"
        ],
        [
            "wryMP8p8k1C",
            "2023W27",
            "vBWtCmNNnCG",
            "10"
        ],
        [
            "wryMP8p8k1C",
            "2023W28",
            "vBWtCmNNnCG",
            "28"
        ],
        [
            "wryMP8p8k1C",
            "2023W29",
            "vBWtCmNNnCG",
            "17"
        ],
        [
            "wryMP8p8k1C",
            "2023W26",
            "c4HrGRJoarj",
            "5"
        ],
        [
            "wryMP8p8k1C",
            "2024W10",
            "quFXhkOJGB4",
            "24"
        ],
        [
            "wryMP8p8k1C",
            "2024W2",
            "c4HrGRJoarj",
            "23"
        ],
        [
            "wryMP8p8k1C",
            "2024W3",
            "c4HrGRJoarj",
            "29"
        ],
        [
            "wryMP8p8k1C",
            "2023W19",
            "vBWtCmNNnCG",
            "24"
        ],
        [
            "wryMP8p8k1C",
            "2024W14",
            "W6sNfkJcXGC",
            "16"
        ],
        [
            "wryMP8p8k1C",
            "2024W7",
            "c4HrGRJoarj",
            "43"
        ],
        [
            "wryMP8p8k1C",
            "2024W1",
            "c4HrGRJoarj",
            "31"
        ],
        [
            "wryMP8p8k1C",
            "2024W8",
            "c4HrGRJoarj",
            "37"
        ],
        [
            "wryMP8p8k1C",
            "2024W9",
            "c4HrGRJoarj",
            "36"
        ],
        [
            "wryMP8p8k1C",
            "2024W10",
            "XKGgynPS1WZ",
            "38"
        ],
        [
            "wryMP8p8k1C",
            "2024W15",
            "W6sNfkJcXGC",
            "8"
        ],
        [
            "wryMP8p8k1C",
            "2023W51",
            "YvLOmtTQD6b",
            "4"
        ],
        [
            "wryMP8p8k1C",
            "2024W10",
            "W6sNfkJcXGC",
            "16"
        ],
        [
            "wryMP8p8k1C",
            "2024W13",
            "XKGgynPS1WZ",
            "38"
        ],
        [
            "wryMP8p8k1C",
            "2023W48",
            "VWGSudnonm5",
            "38"
        ],
        [
            "wryMP8p8k1C",
            "2023W49",
            "VWGSudnonm5",
            "36"
        ],
        [
            "wryMP8p8k1C",
            "2023W50",
            "YvLOmtTQD6b",
            "7"
        ],
        [
            "wryMP8p8k1C",
            "2023W52",
            "YvLOmtTQD6b",
            "7"
        ],
        [
            "wryMP8p8k1C",
            "2024W11",
            "XKGgynPS1WZ",
            "31"
        ],
        [
            "wryMP8p8k1C",
            "2024W12",
            "W6sNfkJcXGC",
            "11"
        ],
        [
            "wryMP8p8k1C",
            "2024W15",
            "XKGgynPS1WZ",
            "29"
        ],
        [
            "wryMP8p8k1C",
            "2023W46",
            "VWGSudnonm5",
            "39"
        ],
        [
            "wryMP8p8k1C",
            "2024W12",
            "XKGgynPS1WZ",
            "23"
        ],
        [
            "wryMP8p8k1C",
            "2024W13",
            "W6sNfkJcXGC",
            "17"
        ],
        [
            "wryMP8p8k1C",
            "2023W20",
            "c4HrGRJoarj",
            "4"
        ],
        [
            "wryMP8p8k1C",
            "2023W44",
            "YvLOmtTQD6b",
            "9"
        ],
        [
            "wryMP8p8k1C",
            "2024W6",
            "c4HrGRJoarj",
            "25"
        ],
        [
            "wryMP8p8k1C",
            "2023W30",
            "c4HrGRJoarj",
            "18"
        ],
        [
            "wryMP8p8k1C",
            "2023W47",
            "VWGSudnonm5",
            "31"
        ],
        [
            "wryMP8p8k1C",
            "2024W4",
            "c4HrGRJoarj",
            "35"
        ],
        [
            "wryMP8p8k1C",
            "2024W5",
            "c4HrGRJoarj",
            "45"
        ],
        [
            "wryMP8p8k1C",
            "2024W11",
            "W6sNfkJcXGC",
            "12"
        ],
        [
            "wryMP8p8k1C",
            "2024W14",
            "XKGgynPS1WZ",
            "45"
        ],
        [
            "wryMP8p8k1C",
            "2023W51",
            "VWGSudnonm5",
            "41"
        ],
        [
            "wryMP8p8k1C",
            "2023W52",
            "VWGSudnonm5",
            "61"
        ],
        [
            "wryMP8p8k1C",
            "2023W19",
            "quFXhkOJGB4",
            "27"
        ],
        [
            "wryMP8p8k1C",
            "2023W17",
            "c4HrGRJoarj",
            "7"
        ],
        [
            "wryMP8p8k1C",
            "2023W31",
            "VWGSudnonm5",
            "1"
        ],
        [
            "wryMP8p8k1C",
            "2023W17",
            "quFXhkOJGB4",
            "26"
        ],
        [
            "wryMP8p8k1C",
            "2023W18",
            "c4HrGRJoarj",
            "6"
        ],
        [
            "wryMP8p8k1C",
            "2023W19",
            "c4HrGRJoarj",
            "3"
        ],
        [
            "wryMP8p8k1C",
            "2023W18",
            "quFXhkOJGB4",
            "20"
        ],
        [
            "wryMP8p8k1C",
            "2023W33",
            "VWGSudnonm5",
            "1"
        ],
        [
            "wryMP8p8k1C",
            "2024W1",
            "quFXhkOJGB4",
            "22"
        ],
        [
            "wryMP8p8k1C",
            "2023W18",
            "W6sNfkJcXGC",
            "6"
        ],
        [
            "wryMP8p8k1C",
            "2024W9",
            "W6sNfkJcXGC",
            "11"
        ],
        [
            "wryMP8p8k1C",
            "2024W2",
            "quFXhkOJGB4",
            "16"
        ],
        [
            "wryMP8p8k1C",
            "2023W17",
            "W6sNfkJcXGC",
            "11"
        ],
        [
            "wryMP8p8k1C",
            "2024W4",
            "quFXhkOJGB4",
            "19"
        ],
        [
            "wryMP8p8k1C",
            "2024W3",
            "quFXhkOJGB4",
            "15"
        ],
        [
            "wryMP8p8k1C",
            "2024W5",
            "quFXhkOJGB4",
            "8"
        ],
        [
            "wryMP8p8k1C",
            "2023W16",
            "W6sNfkJcXGC",
            "11"
        ],
        [
            "wryMP8p8k1C",
            "2023W50",
            "VWGSudnonm5",
            "46"
        ],
        [
            "wryMP8p8k1C",
            "2023W16",
            "c4HrGRJoarj",
            "5"
        ],
        [
            "wryMP8p8k1C",
            "2024W8",
            "quFXhkOJGB4",
            "14"
        ],
        [
            "wryMP8p8k1C",
            "2024W7",
            "quFXhkOJGB4",
            "24"
        ],
        [
            "wryMP8p8k1C",
            "2024W9",
            "quFXhkOJGB4",
            "17"
        ],
        [
            "wryMP8p8k1C",
            "2024W6",
            "quFXhkOJGB4",
            "21"
        ],
        [
            "wryMP8p8k1C",
            "2024W10",
            "rO2RVJWHpCe",
            "40"
        ],
        [
            "wryMP8p8k1C",
            "2023W26",
            "vBWtCmNNnCG",
            "18"
        ],
        [
            "wryMP8p8k1C",
            "2023W24",
            "vBWtCmNNnCG",
            "20"
        ],
        [
            "wryMP8p8k1C",
            "2023W25",
            "vBWtCmNNnCG",
            "12"
        ],
        [
            "wryMP8p8k1C",
            "2023W19",
            "W6sNfkJcXGC",
            "18"
        ],
        [
            "wryMP8p8k1C",
            "2023W22",
            "vBWtCmNNnCG",
            "15"
        ],
        [
            "wryMP8p8k1C",
            "2023W23",
            "vBWtCmNNnCG",
            "26"
        ],
        [
            "wryMP8p8k1C",
            "2023W22",
            "rO2RVJWHpCe",
            "1"
        ],
        [
            "wryMP8p8k1C",
            "2024W15",
            "rO2RVJWHpCe",
            "27"
        ],
        [
            "wryMP8p8k1C",
            "2023W21",
            "rO2RVJWHpCe",
            "1"
        ],
        [
            "wryMP8p8k1C",
            "2024W14",
            "rO2RVJWHpCe",
            "19"
        ],
        [
            "wryMP8p8k1C",
            "2023W16",
            "quFXhkOJGB4",
            "17"
        ],
        [
            "wryMP8p8k1C",
            "2024W14",
            "vBWtCmNNnCG",
            "40"
        ],
        [
            "wryMP8p8k1C",
            "2024W15",
            "vBWtCmNNnCG",
            "50"
        ],
        [
            "wryMP8p8k1C",
            "2024W11",
            "rO2RVJWHpCe",
            "44"
        ],
        [
            "wryMP8p8k1C",
            "2024W13",
            "rO2RVJWHpCe",
            "36"
        ],
        [
            "wryMP8p8k1C",
            "2023W20",
            "vBWtCmNNnCG",
            "24"
        ],
        [
            "wryMP8p8k1C",
            "2023W21",
            "vBWtCmNNnCG",
            "18"
        ],
        [
            "wryMP8p8k1C",
            "2024W13",
            "vBWtCmNNnCG",
            "43"
        ],
        [
            "wryMP8p8k1C",
            "2024W12",
            "rO2RVJWHpCe",
            "33"
        ],
        [
            "wryMP8p8k1C",
            "2023W49",
            "dOhqCNenSjS",
            "4"
        ],
        [
            "wryMP8p8k1C",
            "2024W10",
            "vBWtCmNNnCG",
            "56"
        ],
        [
            "wryMP8p8k1C",
            "2023W45",
            "c4HrGRJoarj",
            "13"
        ],
        [
            "wryMP8p8k1C",
            "2023W47",
            "c4HrGRJoarj",
            "10"
        ],
        [
            "wryMP8p8k1C",
            "2023W28",
            "quFXhkOJGB4",
            "11"
        ],
        [
            "wryMP8p8k1C",
            "2024W12",
            "vBWtCmNNnCG",
            "40"
        ],
        [
            "wryMP8p8k1C",
            "2023W29",
            "rO2RVJWHpCe",
            "3"
        ],
        [
            "wryMP8p8k1C",
            "2023W43",
            "c4HrGRJoarj",
            "1"
        ],
        [
            "wryMP8p8k1C",
            "2023W43",
            "dOhqCNenSjS",
            "1"
        ],
        [
            "wryMP8p8k1C",
            "2024W8",
            "VWGSudnonm5",
            "61"
        ],
        [
            "wryMP8p8k1C",
            "2023W23",
            "rO2RVJWHpCe",
            "3"
        ],
        [
            "wryMP8p8k1C",
            "2023W28",
            "W6sNfkJcXGC",
            "2"
        ],
        [
            "wryMP8p8k1C",
            "2023W20",
            "quFXhkOJGB4",
            "26"
        ],
        [
            "wryMP8p8k1C",
            "2024W2",
            "VWGSudnonm5",
            "41"
        ],
        [
            "wryMP8p8k1C",
            "2024W6",
            "VWGSudnonm5",
            "46"
        ],
        [
            "wryMP8p8k1C",
            "2023W26",
            "W6sNfkJcXGC",
            "3"
        ],
        [
            "wryMP8p8k1C",
            "2023W45",
            "dOhqCNenSjS",
            "15"
        ],
        [
            "wryMP8p8k1C",
            "2023W49",
            "c4HrGRJoarj",
            "17"
        ],
        [
            "wryMP8p8k1C",
            "2023W17",
            "XKGgynPS1WZ",
            "7"
        ],
        [
            "wryMP8p8k1C",
            "2023W19",
            "XKGgynPS1WZ",
            "44"
        ],
        [
            "wryMP8p8k1C",
            "2023W47",
            "dOhqCNenSjS",
            "10"
        ],
        [
            "wryMP8p8k1C",
            "2024W4",
            "VWGSudnonm5",
            "59"
        ],
        [
            "wryMP8p8k1C",
            "2023W22",
            "W6sNfkJcXGC",
            "15"
        ],
        [
            "wryMP8p8k1C",
            "2024W4",
            "YvLOmtTQD6b",
            "7"
        ],
        [
            "wryMP8p8k1C",
            "2024W6",
            "YvLOmtTQD6b",
            "7"
        ],
        [
            "wryMP8p8k1C",
            "2024W2",
            "XKGgynPS1WZ",
            "30"
        ],
        [
            "wryMP8p8k1C",
            "2024W4",
            "XKGgynPS1WZ",
            "33"
        ],
        [
            "wryMP8p8k1C",
            "2023W20",
            "W6sNfkJcXGC",
            "13"
        ],
        [
            "wryMP8p8k1C",
            "2023W24",
            "W6sNfkJcXGC",
            "7"
        ],
        [
            "wryMP8p8k1C",
            "2023W31",
            "W6sNfkJcXGC",
            "4"
        ],
        [
            "wryMP8p8k1C",
            "2023W35",
            "W6sNfkJcXGC",
            "7"
        ],
        [
            "wryMP8p8k1C",
            "2024W10",
            "FRmrFTE63D0",
            "25"
        ],
        [
            "wryMP8p8k1C",
            "2024W2",
            "YvLOmtTQD6b",
            "9"
        ],
        [
            "wryMP8p8k1C",
            "2023W50",
            "c4HrGRJoarj",
            "23"
        ],
        [
            "wryMP8p8k1C",
            "2024W12",
            "c4HrGRJoarj",
            "16"
        ],
        [
            "wryMP8p8k1C",
            "2024W14",
            "c4HrGRJoarj",
            "37"
        ],
        [
            "wryMP8p8k1C",
            "2024W7",
            "W6sNfkJcXGC",
            "16"
        ],
        [
            "wryMP8p8k1C",
            "2024W14",
            "FRmrFTE63D0",
            "29"
        ],
        [
            "wryMP8p8k1C",
            "2023W21",
            "XKGgynPS1WZ",
            "23"
        ],
        [
            "wryMP8p8k1C",
            "2024W12",
            "FRmrFTE63D0",
            "34"
        ],
        [
            "wryMP8p8k1C",
            "2024W8",
            "YvLOmtTQD6b",
            "17"
        ],
        [
            "wryMP8p8k1C",
            "2023W52",
            "c4HrGRJoarj",
            "29"
        ],
        [
            "wryMP8p8k1C",
            "2024W10",
            "c4HrGRJoarj",
            "42"
        ],
        [
            "wryMP8p8k1C",
            "2024W3",
            "W6sNfkJcXGC",
            "14"
        ],
        [
            "wryMP8p8k1C",
            "2024W5",
            "W6sNfkJcXGC",
            "20"
        ],
        [
            "wryMP8p8k1C",
            "2024W6",
            "XKGgynPS1WZ",
            "30"
        ],
        [
            "wryMP8p8k1C",
            "2024W8",
            "XKGgynPS1WZ",
            "36"
        ],
        [
            "wryMP8p8k1C",
            "2023W32",
            "YvLOmtTQD6b",
            "1"
        ],
        [
            "wryMP8p8k1C",
            "2023W25",
            "XKGgynPS1WZ",
            "9"
        ],
        [
            "wryMP8p8k1C",
            "2024W1",
            "W6sNfkJcXGC",
            "21"
        ],
        [
            "wryMP8p8k1C",
            "2023W23",
            "XKGgynPS1WZ",
            "21"
        ],
        [
            "wryMP8p8k1C",
            "2023W27",
            "XKGgynPS1WZ",
            "13"
        ],
        [
            "wryMP8p8k1C",
            "2023W19",
            "FRmrFTE63D0",
            "11"
        ],
        [
            "wryMP8p8k1C",
            "2023W36",
            "rO2RVJWHpCe",
            "1"
        ],
        [
            "wryMP8p8k1C",
            "2023W36",
            "YvLOmtTQD6b",
            "2"
        ],
        [
            "wryMP8p8k1C",
            "2023W34",
            "rO2RVJWHpCe",
            "2"
        ],
        [
            "wryMP8p8k1C",
            "2023W33",
            "dOhqCNenSjS",
            "2"
        ],
        [
            "wryMP8p8k1C",
            "2023W29",
            "XKGgynPS1WZ",
            "2"
        ],
        [
            "wryMP8p8k1C",
            "2023W17",
            "vBWtCmNNnCG",
            "7"
        ],
        [
            "wryMP8p8k1C",
            "2023W38",
            "vBWtCmNNnCG",
            "2"
        ],
        [
            "wryMP8p8k1C",
            "2023W17",
            "FRmrFTE63D0",
            "5"
        ],
        [
            "wryMP8p8k1C",
            "2023W38",
            "rO2RVJWHpCe",
            "5"
        ],
        [
            "wryMP8p8k1C",
            "2024W6",
            "rO2RVJWHpCe",
            "30"
        ],
        [
            "wryMP8p8k1C",
            "2024W4",
            "rO2RVJWHpCe",
            "21"
        ],
        [
            "wryMP8p8k1C",
            "2024W8",
            "rO2RVJWHpCe",
            "23"
        ],
        [
            "wryMP8p8k1C",
            "2023W51",
            "hdeC7uX9Cko",
            "68"
        ],
        [
            "wryMP8p8k1C",
            "2024W12",
            "quFXhkOJGB4",
            "24"
        ],
        [
            "wryMP8p8k1C",
            "2024W2",
            "rO2RVJWHpCe",
            "39"
        ],
        [
            "wryMP8p8k1C",
            "2024W14",
            "quFXhkOJGB4",
            "20"
        ],
        [
            "wryMP8p8k1C",
            "2023W36",
            "vBWtCmNNnCG",
            "15"
        ],
        [
            "wryMP8p8k1C",
            "2024W10",
            "K27JzTKmBKh",
            "11"
        ],
        [
            "wryMP8p8k1C",
            "2024W12",
            "K27JzTKmBKh",
            "18"
        ],
        [
            "wryMP8p8k1C",
            "2023W52",
            "dOhqCNenSjS",
            "10"
        ],
        [
            "wryMP8p8k1C",
            "2023W22",
            "quFXhkOJGB4",
            "7"
        ],
        [
            "wryMP8p8k1C",
            "2023W32",
            "vBWtCmNNnCG",
            "22"
        ],
        [
            "wryMP8p8k1C",
            "2023W34",
            "vBWtCmNNnCG",
            "7"
        ],
        [
            "wryMP8p8k1C",
            "2024W14",
            "K27JzTKmBKh",
            "17"
        ],
        [
            "wryMP8p8k1C",
            "2023W24",
            "quFXhkOJGB4",
            "9"
        ],
        [
            "wryMP8p8k1C",
            "2023W32",
            "rO2RVJWHpCe",
            "3"
        ],
        [
            "wryMP8p8k1C",
            "2023W45",
            "quFXhkOJGB4",
            "41"
        ],
        [
            "wryMP8p8k1C",
            "2023W51",
            "vBWtCmNNnCG",
            "48"
        ],
        [
            "wryMP8p8k1C",
            "2023W20",
            "K27JzTKmBKh",
            "3"
        ],
        [
            "wryMP8p8k1C",
            "2023W26",
            "quFXhkOJGB4",
            "10"
        ],
        [
            "wryMP8p8k1C",
            "2023W30",
            "vBWtCmNNnCG",
            "22"
        ],
        [
            "wryMP8p8k1C",
            "2024W6",
            "vBWtCmNNnCG",
            "30"
        ],
        [
            "wryMP8p8k1C",
            "2023W50",
            "dOhqCNenSjS",
            "1"
        ],
        [
            "wryMP8p8k1C",
            "2023W30",
            "rO2RVJWHpCe",
            "2"
        ],
        [
            "wryMP8p8k1C",
            "2023W47",
            "quFXhkOJGB4",
            "19"
        ],
        [
            "wryMP8p8k1C",
            "2023W36",
            "XKGgynPS1WZ",
            "1"
        ],
        [
            "wryMP8p8k1C",
            "2024W11",
            "TOgZ99Jv0bN",
            "37"
        ],
        [
            "wryMP8p8k1C",
            "2023W37",
            "XKGgynPS1WZ",
            "1"
        ],
        [
            "wryMP8p8k1C",
            "2023W26",
            "dOhqCNenSjS",
            "3"
        ],
        [
            "wryMP8p8k1C",
            "2023W26",
            "FRmrFTE63D0",
            "18"
        ],
        [
            "wryMP8p8k1C",
            "2024W13",
            "RdNV4tTRNEo",
            "28"
        ],
        [
            "wryMP8p8k1C",
            "2024W10",
            "TOgZ99Jv0bN",
            "66"
        ],
        [
            "wryMP8p8k1C",
            "2024W14",
            "TOgZ99Jv0bN",
            "63"
        ],
        [
            "wryMP8p8k1C",
            "2024W13",
            "VWGSudnonm5",
            "61"
        ],
        [
            "wryMP8p8k1C",
            "2023W52",
            "pFCZqWnXtoU",
            "48"
        ],
        [
            "wryMP8p8k1C",
            "2023W24",
            "K27JzTKmBKh",
            "1"
        ],
        [
            "wryMP8p8k1C",
            "2023W46",
            "rO2RVJWHpCe",
            "44"
        ],
        [
            "wryMP8p8k1C",
            "2024W15",
            "TOgZ99Jv0bN",
            "73"
        ],
        [
            "wryMP8p8k1C",
            "2024W11",
            "sv6c7CpPcrc",
            "21"
        ],
        [
            "wryMP8p8k1C",
            "2024W12",
            "RdNV4tTRNEo",
            "12"
        ],
        [
            "wryMP8p8k1C",
            "2024W10",
            "sv6c7CpPcrc",
            "21"
        ],
        [
            "wryMP8p8k1C",
            "2023W23",
            "FRmrFTE63D0",
            "42"
        ],
        [
            "wryMP8p8k1C",
            "2023W45",
            "rO2RVJWHpCe",
            "39"
        ],
        [
            "wryMP8p8k1C",
            "2023W21",
            "dOhqCNenSjS",
            "4"
        ],
        [
            "wryMP8p8k1C",
            "2023W29",
            "dOhqCNenSjS",
            "1"
        ],
        [
            "wryMP8p8k1C",
            "2023W22",
            "dOhqCNenSjS",
            "9"
        ],
        [
            "wryMP8p8k1C",
            "2023W49",
            "W6sNfkJcXGC",
            "12"
        ],
        [
            "wryMP8p8k1C",
            "2023W41",
            "quFXhkOJGB4",
            "5"
        ],
        [
            "wryMP8p8k1C",
            "2023W48",
            "W6sNfkJcXGC",
            "12"
        ],
        [
            "wryMP8p8k1C",
            "2024W12",
            "VWGSudnonm5",
            "60"
        ],
        [
            "wryMP8p8k1C",
            "2023W40",
            "quFXhkOJGB4",
            "2"
        ],
        [
            "wryMP8p8k1C",
            "2023W51",
            "pFCZqWnXtoU",
            "40"
        ],
        [
            "wryMP8p8k1C",
            "2023W27",
            "FRmrFTE63D0",
            "14"
        ],
        [
            "wryMP8p8k1C",
            "2023W49",
            "rO2RVJWHpCe",
            "57"
        ],
        [
            "wryMP8p8k1C",
            "2023W25",
            "dOhqCNenSjS",
            "2"
        ],
        [
            "wryMP8p8k1C",
            "2023W44",
            "W6sNfkJcXGC",
            "14"
        ],
        [
            "wryMP8p8k1C",
            "2024W7",
            "FRmrFTE63D0",
            "23"
        ],
        [
            "wryMP8p8k1C",
            "2024W1",
            "hRQsZhmvqgS",
            "20"
        ],
        [
            "wryMP8p8k1C",
            "2024W4",
            "FRmrFTE63D0",
            "39"
        ],
        [
            "wryMP8p8k1C",
            "2024W8",
            "FRmrFTE63D0",
            "21"
        ],
        [
            "wryMP8p8k1C",
            "2023W45",
            "W6sNfkJcXGC",
            "22"
        ],
        [
            "wryMP8p8k1C",
            "2024W3",
            "FRmrFTE63D0",
            "31"
        ],
        [
            "wryMP8p8k1C",
            "2024W2",
            "hRQsZhmvqgS",
            "2"
        ],
        [
            "wryMP8p8k1C",
            "2024W15",
            "sv6c7CpPcrc",
            "18"
        ],
        [
            "wryMP8p8k1C",
            "2024W14",
            "sv6c7CpPcrc",
            "7"
        ],
        [
            "wryMP8p8k1C",
            "2023W33",
            "FRmrFTE63D0",
            "1"
        ],
        [
            "wryMP8p8k1C",
            "2023W22",
            "FRmrFTE63D0",
            "48"
        ],
        [
            "wryMP8p8k1C",
            "2023W49",
            "pFCZqWnXtoU",
            "31"
        ],
        [
            "wryMP8p8k1C",
            "2023W32",
            "XKGgynPS1WZ",
            "4"
        ],
        [
            "wryMP8p8k1C",
            "2023W50",
            "W6sNfkJcXGC",
            "11"
        ],
        [
            "wryMP8p8k1C",
            "2023W43",
            "XKGgynPS1WZ",
            "1"
        ],
        [
            "wryMP8p8k1C",
            "2024W12",
            "YvLOmtTQD6b",
            "11"
        ],
        [
            "wryMP8p8k1C",
            "2023W33",
            "XKGgynPS1WZ",
            "2"
        ],
        [
            "wryMP8p8k1C",
            "2023W51",
            "W6sNfkJcXGC",
            "8"
        ],
        [
            "wryMP8p8k1C",
            "2024W13",
            "YvLOmtTQD6b",
            "3"
        ],
        [
            "wryMP8p8k1C",
            "2023W30",
            "FRmrFTE63D0",
            "8"
        ],
        [
            "wryMP8p8k1C",
            "2023W24",
            "hRQsZhmvqgS",
            "6"
        ],
        [
            "wryMP8p8k1C",
            "2023W25",
            "hRQsZhmvqgS",
            "11"
        ],
        [
            "wryMP8p8k1C",
            "2023W18",
            "K27JzTKmBKh",
            "2"
        ],
        [
            "wryMP8p8k1C",
            "2023W46",
            "pFCZqWnXtoU",
            "50"
        ],
        [
            "wryMP8p8k1C",
            "2023W38",
            "quFXhkOJGB4",
            "3"
        ],
        [
            "wryMP8p8k1C",
            "2023W45",
            "pFCZqWnXtoU",
            "41"
        ],
        [
            "wryMP8p8k1C",
            "2024W10",
            "hRQsZhmvqgS",
            "15"
        ],
        [
            "wryMP8p8k1C",
            "2024W14",
            "hRQsZhmvqgS",
            "15"
        ],
        [
            "wryMP8p8k1C",
            "2023W38",
            "W6sNfkJcXGC",
            "4"
        ],
        [
            "wryMP8p8k1C",
            "2023W30",
            "quFXhkOJGB4",
            "5"
        ],
        [
            "wryMP8p8k1C",
            "2024W11",
            "hRQsZhmvqgS",
            "5"
        ],
        [
            "wryMP8p8k1C",
            "2024W15",
            "hRQsZhmvqgS",
            "19"
        ],
        [
            "wryMP8p8k1C",
            "2024W1",
            "K27JzTKmBKh",
            "18"
        ],
        [
            "wryMP8p8k1C",
            "2023W37",
            "W6sNfkJcXGC",
            "2"
        ],
        [
            "wryMP8p8k1C",
            "2023W17",
            "TOgZ99Jv0bN",
            "3"
        ],
        [
            "wryMP8p8k1C",
            "2023W51",
            "quFXhkOJGB4",
            "15"
        ],
        [
            "wryMP8p8k1C",
            "2023W21",
            "hRQsZhmvqgS",
            "8"
        ],
        [
            "wryMP8p8k1C",
            "2023W50",
            "quFXhkOJGB4",
            "30"
        ],
        [
            "wryMP8p8k1C",
            "2023W20",
            "hRQsZhmvqgS",
            "6"
        ],
        [
            "wryMP8p8k1C",
            "2024W5",
            "K27JzTKmBKh",
            "13"
        ],
        [
            "wryMP8p8k1C",
            "2023W44",
            "hdeC7uX9Cko",
            "66"
        ],
        [
            "wryMP8p8k1C",
            "2023W41",
            "MBZYTqkEgwf",
            "3"
        ],
        [
            "wryMP8p8k1C",
            "2023W45",
            "MBZYTqkEgwf",
            "43"
        ],
        [
            "wryMP8p8k1C",
            "2024W2",
            "K27JzTKmBKh",
            "15"
        ],
        [
            "wryMP8p8k1C",
            "2024W6",
            "K27JzTKmBKh",
            "10"
        ],
        [
            "wryMP8p8k1C",
            "2023W46",
            "vBWtCmNNnCG",
            "25"
        ],
        [
            "wryMP8p8k1C",
            "2023W42",
            "rO2RVJWHpCe",
            "1"
        ],
        [
            "wryMP8p8k1C",
            "2023W33",
            "quFXhkOJGB4",
            "5"
        ],
        [
            "wryMP8p8k1C",
            "2023W45",
            "vBWtCmNNnCG",
            "43"
        ],
        [
            "wryMP8p8k1C",
            "2023W48",
            "hdeC7uX9Cko",
            "54"
        ],
        [
            "wryMP8p8k1C",
            "2023W49",
            "MBZYTqkEgwf",
            "29"
        ],
        [
            "wryMP8p8k1C",
            "2023W34",
            "quFXhkOJGB4",
            "1"
        ],
        [
            "wryMP8p8k1C",
            "2023W37",
            "quFXhkOJGB4",
            "3"
        ],
        [
            "wryMP8p8k1C",
            "2023W28",
            "hRQsZhmvqgS",
            "3"
        ],
        [
            "wryMP8p8k1C",
            "2024W9",
            "K27JzTKmBKh",
            "14"
        ],
        [
            "wryMP8p8k1C",
            "2023W46",
            "MBZYTqkEgwf",
            "43"
        ],
        [
            "wryMP8p8k1C",
            "2023W47",
            "hdeC7uX9Cko",
            "46"
        ],
        [
            "wryMP8p8k1C",
            "2023W41",
            "vBWtCmNNnCG",
            "1"
        ],
        [
            "wryMP8p8k1C",
            "2023W29",
            "hRQsZhmvqgS",
            "1"
        ],
        [
            "wryMP8p8k1C",
            "2023W42",
            "vBWtCmNNnCG",
            "1"
        ],
        [
            "wryMP8p8k1C",
            "2023W35",
            "hRQsZhmvqgS",
            "9"
        ],
        [
            "wryMP8p8k1C",
            "2024W11",
            "vBWtCmNNnCG",
            "44"
        ],
        [
            "wryMP8p8k1C",
            "2024W9",
            "TOgZ99Jv0bN",
            "55"
        ],
        [
            "wryMP8p8k1C",
            "2024W5",
            "sv6c7CpPcrc",
            "29"
        ],
        [
            "wryMP8p8k1C",
            "2023W28",
            "rO2RVJWHpCe",
            "9"
        ],
        [
            "wryMP8p8k1C",
            "2023W48",
            "FRmrFTE63D0",
            "38"
        ],
        [
            "wryMP8p8k1C",
            "2023W31",
            "pFCZqWnXtoU",
            "1"
        ],
        [
            "wryMP8p8k1C",
            "2023W35",
            "pFCZqWnXtoU",
            "1"
        ],
        [
            "wryMP8p8k1C",
            "2023W46",
            "K27JzTKmBKh",
            "17"
        ],
        [
            "wryMP8p8k1C",
            "2023W16",
            "XKGgynPS1WZ",
            "8"
        ],
        [
            "wryMP8p8k1C",
            "2023W24",
            "rO2RVJWHpCe",
            "2"
        ],
        [
            "wryMP8p8k1C",
            "2023W44",
            "c4HrGRJoarj",
            "19"
        ],
        [
            "wryMP8p8k1C",
            "2024W1",
            "TOgZ99Jv0bN",
            "79"
        ],
        [
            "wryMP8p8k1C",
            "2024W15",
            "dOhqCNenSjS",
            "33"
        ],
        [
            "wryMP8p8k1C",
            "2024W3",
            "RdNV4tTRNEo",
            "27"
        ],
        [
            "wryMP8p8k1C",
            "2024W3",
            "VWGSudnonm5",
            "57"
        ],
        [
            "wryMP8p8k1C",
            "2024W7",
            "VWGSudnonm5",
            "61"
        ],
        [
            "wryMP8p8k1C",
            "2023W31",
            "hRQsZhmvqgS",
            "10"
        ],
        [
            "wryMP8p8k1C",
            "2024W3",
            "hdeC7uX9Cko",
            "79"
        ],
        [
            "wryMP8p8k1C",
            "2024W1",
            "sv6c7CpPcrc",
            "32"
        ],
        [
            "wryMP8p8k1C",
            "2023W27",
            "W6sNfkJcXGC",
            "3"
        ],
        [
            "wryMP8p8k1C",
            "2023W49",
            "vBWtCmNNnCG",
            "33"
        ],
        [
            "wryMP8p8k1C",
            "2023W48",
            "c4HrGRJoarj",
            "33"
        ],
        [
            "wryMP8p8k1C",
            "2023W46",
            "dOhqCNenSjS",
            "17"
        ],
        [
            "wryMP8p8k1C",
            "2023W23",
            "W6sNfkJcXGC",
            "8"
        ],
        [
            "wryMP8p8k1C",
            "2023W34",
            "W6sNfkJcXGC",
            "2"
        ],
        [
            "wryMP8p8k1C",
            "2023W18",
            "sv6c7CpPcrc",
            "1"
        ],
        [
            "wryMP8p8k1C",
            "2023W28",
            "sv6c7CpPcrc",
            "3"
        ],
        [
            "wryMP8p8k1C",
            "2024W3",
            "YvLOmtTQD6b",
            "5"
        ],
        [
            "wryMP8p8k1C",
            "2024W3",
            "XKGgynPS1WZ",
            "24"
        ],
        [
            "wryMP8p8k1C",
            "2024W8",
            "W6sNfkJcXGC",
            "9"
        ],
        [
            "wryMP8p8k1C",
            "2024W13",
            "c4HrGRJoarj",
            "40"
        ],
        [
            "wryMP8p8k1C",
            "2023W50",
            "XKGgynPS1WZ",
            "22"
        ],
        [
            "wryMP8p8k1C",
            "2023W52",
            "sv6c7CpPcrc",
            "36"
        ],
        [
            "wryMP8p8k1C",
            "2023W44",
            "FRmrFTE63D0",
            "38"
        ],
        [
            "wryMP8p8k1C",
            "2024W7",
            "RdNV4tTRNEo",
            "20"
        ],
        [
            "wryMP8p8k1C",
            "2023W28",
            "pFCZqWnXtoU",
            "20"
        ],
        [
            "wryMP8p8k1C",
            "2023W20",
            "sv6c7CpPcrc",
            "2"
        ],
        [
            "wryMP8p8k1C",
            "2023W50",
            "FRmrFTE63D0",
            "44"
        ],
        [
            "wryMP8p8k1C",
            "2024W13",
            "FRmrFTE63D0",
            "28"
        ],
        [
            "wryMP8p8k1C",
            "2023W23",
            "RdNV4tTRNEo",
            "1"
        ],
        [
            "wryMP8p8k1C",
            "2024W5",
            "TOgZ99Jv0bN",
            "66"
        ],
        [
            "wryMP8p8k1C",
            "2024W9",
            "sv6c7CpPcrc",
            "13"
        ],
        [
            "wryMP8p8k1C",
            "2023W22",
            "XKGgynPS1WZ",
            "40"
        ],
        [
            "wryMP8p8k1C",
            "2023W30",
            "W6sNfkJcXGC",
            "1"
        ],
        [
            "wryMP8p8k1C",
            "2024W7",
            "YvLOmtTQD6b",
            "4"
        ],
        [
            "wryMP8p8k1C",
            "2023W40",
            "c4HrGRJoarj",
            "1"
        ],
        [
            "wryMP8p8k1C",
            "2023W51",
            "c4HrGRJoarj",
            "30"
        ],
        [
            "wryMP8p8k1C",
            "2023W52",
            "TOgZ99Jv0bN",
            "65"
        ],
        [
            "wryMP8p8k1C",
            "2024W4",
            "W6sNfkJcXGC",
            "16"
        ],
        [
            "wryMP8p8k1C",
            "2024W7",
            "XKGgynPS1WZ",
            "28"
        ],
        [
            "wryMP8p8k1C",
            "2023W47",
            "XKGgynPS1WZ",
            "26"
        ],
        [
            "wryMP8p8k1C",
            "2023W26",
            "XKGgynPS1WZ",
            "7"
        ],
        [
            "wryMP8p8k1C",
            "2023W37",
            "FRmrFTE63D0",
            "2"
        ],
        [
            "wryMP8p8k1C",
            "2023W35",
            "rO2RVJWHpCe",
            "3"
        ],
        [
            "wryMP8p8k1C",
            "2024W1",
            "MBZYTqkEgwf",
            "29"
        ],
        [
            "wryMP8p8k1C",
            "2024W5",
            "MBZYTqkEgwf",
            "25"
        ],
        [
            "wryMP8p8k1C",
            "2024W9",
            "hRQsZhmvqgS",
            "13"
        ],
        [
            "wryMP8p8k1C",
            "2024W5",
            "pFCZqWnXtoU",
            "40"
        ],
        [
            "wryMP8p8k1C",
            "2024W5",
            "hRQsZhmvqgS",
            "19"
        ],
        [
            "wryMP8p8k1C",
            "2023W16",
            "FRmrFTE63D0",
            "3"
        ],
        [
            "wryMP8p8k1C",
            "2023W18",
            "vBWtCmNNnCG",
            "20"
        ],
        [
            "wryMP8p8k1C",
            "2023W39",
            "vBWtCmNNnCG",
            "4"
        ],
        [
            "wryMP8p8k1C",
            "2023W36",
            "dOhqCNenSjS",
            "1"
        ],
        [
            "wryMP8p8k1C",
            "2024W1",
            "pFCZqWnXtoU",
            "35"
        ],
        [
            "wryMP8p8k1C",
            "2024W6",
            "dOhqCNenSjS",
            "13"
        ],
        [
            "wryMP8p8k1C",
            "2023W50",
            "hdeC7uX9Cko",
            "76"
        ],
        [
            "wryMP8p8k1C",
            "2024W13",
            "quFXhkOJGB4",
            "17"
        ],
        [
            "wryMP8p8k1C",
            "2023W31",
            "MBZYTqkEgwf",
            "14"
        ],
        [
            "wryMP8p8k1C",
            "2023W35",
            "MBZYTqkEgwf",
            "4"
        ],
        [
            "wryMP8p8k1C",
            "2023W52",
            "MBZYTqkEgwf",
            "32"
        ],
        [
            "wryMP8p8k1C",
            "2024W9",
            "MBZYTqkEgwf",
            "23"
        ],
        [
            "wryMP8p8k1C",
            "2023W35",
            "vBWtCmNNnCG",
            "15"
        ],
        [
            "wryMP8p8k1C",
            "2024W1",
            "rO2RVJWHpCe",
            "37"
        ],
        [
            "wryMP8p8k1C",
            "2024W9",
            "rO2RVJWHpCe",
            "26"
        ],
        [
            "wryMP8p8k1C",
            "2024W11",
            "K27JzTKmBKh",
            "12"
        ],
        [
            "wryMP8p8k1C",
            "2023W39",
            "MBZYTqkEgwf",
            "3"
        ],
        [
            "wryMP8p8k1C",
            "2023W52",
            "rO2RVJWHpCe",
            "46"
        ],
        [
            "wryMP8p8k1C",
            "2024W7",
            "hdeC7uX9Cko",
            "77"
        ],
        [
            "wryMP8p8k1C",
            "2023W23",
            "quFXhkOJGB4",
            "12"
        ],
        [
            "wryMP8p8k1C",
            "2023W18",
            "MBZYTqkEgwf",
            "3"
        ],
        [
            "wryMP8p8k1C",
            "2023W31",
            "rO2RVJWHpCe",
            "5"
        ],
        [
            "wryMP8p8k1C",
            "2023W44",
            "quFXhkOJGB4",
            "31"
        ],
        [
            "wryMP8p8k1C",
            "2023W21",
            "K27JzTKmBKh",
            "3"
        ],
        [
            "wryMP8p8k1C",
            "2023W39",
            "hRQsZhmvqgS",
            "4"
        ],
        [
            "wryMP8p8k1C",
            "2023W27",
            "quFXhkOJGB4",
            "9"
        ],
        [
            "wryMP8p8k1C",
            "2023W48",
            "quFXhkOJGB4",
            "21"
        ],
        [
            "wryMP8p8k1C",
            "2023W52",
            "vBWtCmNNnCG",
            "52"
        ],
        [
            "wryMP8p8k1C",
            "2024W2",
            "dOhqCNenSjS",
            "18"
        ],
        [
            "wryMP8p8k1C",
            "2023W18",
            "hRQsZhmvqgS",
            "3"
        ],
        [
            "wryMP8p8k1C",
            "2023W31",
            "vBWtCmNNnCG",
            "38"
        ],
        [
            "wryMP8p8k1C",
            "2024W5",
            "rO2RVJWHpCe",
            "19"
        ],
        [
            "wryMP8p8k1C",
            "2024W15",
            "K27JzTKmBKh",
            "9"
        ],
        [
            "wryMP8p8k1C",
            "2023W18",
            "pFCZqWnXtoU",
            "68"
        ],
        [
            "wryMP8p8k1C",
            "2023W19",
            "pFCZqWnXtoU",
            "44"
        ],
        [
            "wryMP8p8k1C",
            "2023W48",
            "RdNV4tTRNEo",
            "20"
        ],
        [
            "wryMP8p8k1C",
            "2024W10",
            "hdeC7uX9Cko",
            "66"
        ],
        [
            "wryMP8p8k1C",
            "2023W49",
            "RdNV4tTRNEo",
            "18"
        ],
        [
            "wryMP8p8k1C",
            "2023W46",
            "TOgZ99Jv0bN",
            "47"
        ],
        [
            "wryMP8p8k1C",
            "2024W11",
            "hdeC7uX9Cko",
            "95"
        ],
        [
            "wryMP8p8k1C",
            "2023W50",
            "hRQsZhmvqgS",
            "5"
        ],
        [
            "wryMP8p8k1C",
            "2023W47",
            "TOgZ99Jv0bN",
            "39"
        ],
        [
            "wryMP8p8k1C",
            "2023W48",
            "TOgZ99Jv0bN",
            "57"
        ],
        [
            "wryMP8p8k1C",
            "2023W52",
            "hRQsZhmvqgS",
            "18"
        ],
        [
            "wryMP8p8k1C",
            "2023W51",
            "hRQsZhmvqgS",
            "6"
        ],
        [
            "wryMP8p8k1C",
            "2023W49",
            "TOgZ99Jv0bN",
            "62"
        ],
        [
            "wryMP8p8k1C",
            "2023W48",
            "sv6c7CpPcrc",
            "30"
        ],
        [
            "wryMP8p8k1C",
            "2023W47",
            "sv6c7CpPcrc",
            "37"
        ],
        [
            "wryMP8p8k1C",
            "2023W49",
            "sv6c7CpPcrc",
            "31"
        ],
        [
            "wryMP8p8k1C",
            "2023W38",
            "sv6c7CpPcrc",
            "1"
        ],
        [
            "wryMP8p8k1C",
            "2023W46",
            "sv6c7CpPcrc",
            "42"
        ],
        [
            "wryMP8p8k1C",
            "2023W35",
            "sv6c7CpPcrc",
            "1"
        ],
        [
            "wryMP8p8k1C",
            "2023W45",
            "TOgZ99Jv0bN",
            "64"
        ],
        [
            "wryMP8p8k1C",
            "2023W37",
            "sv6c7CpPcrc",
            "1"
        ],
        [
            "wryMP8p8k1C",
            "2024W8",
            "pFCZqWnXtoU",
            "43"
        ],
        [
            "wryMP8p8k1C",
            "2024W9",
            "pFCZqWnXtoU",
            "59"
        ],
        [
            "wryMP8p8k1C",
            "2023W47",
            "RdNV4tTRNEo",
            "12"
        ],
        [
            "wryMP8p8k1C",
            "2023W33",
            "TOgZ99Jv0bN",
            "5"
        ],
        [
            "wryMP8p8k1C",
            "2023W44",
            "TOgZ99Jv0bN",
            "67"
        ],
        [
            "wryMP8p8k1C",
            "2023W17",
            "pFCZqWnXtoU",
            "38"
        ],
        [
            "wryMP8p8k1C",
            "2023W46",
            "RdNV4tTRNEo",
            "21"
        ],
        [
            "wryMP8p8k1C",
            "2023W32",
            "TOgZ99Jv0bN",
            "3"
        ],
        [
            "wryMP8p8k1C",
            "2023W31",
            "sv6c7CpPcrc",
            "1"
        ],
        [
            "wryMP8p8k1C",
            "2023W16",
            "pFCZqWnXtoU",
            "21"
        ],
        [
            "wryMP8p8k1C",
            "2023W44",
            "sv6c7CpPcrc",
            "41"
        ],
        [
            "wryMP8p8k1C",
            "2023W45",
            "sv6c7CpPcrc",
            "48"
        ],
        [
            "wryMP8p8k1C",
            "2023W45",
            "RdNV4tTRNEo",
            "17"
        ],
        [
            "wryMP8p8k1C",
            "2023W42",
            "TOgZ99Jv0bN",
            "1"
        ],
        [
            "wryMP8p8k1C",
            "2023W34",
            "sv6c7CpPcrc",
            "4"
        ],
        [
            "wryMP8p8k1C",
            "2023W44",
            "RdNV4tTRNEo",
            "15"
        ],
        [
            "wryMP8p8k1C",
            "2023W30",
            "TOgZ99Jv0bN",
            "1"
        ],
        [
            "wryMP8p8k1C",
            "2023W33",
            "sv6c7CpPcrc",
            "1"
        ],
        [
            "wryMP8p8k1C",
            "2023W22",
            "pFCZqWnXtoU",
            "41"
        ],
        [
            "wryMP8p8k1C",
            "2023W23",
            "pFCZqWnXtoU",
            "46"
        ],
        [
            "wryMP8p8k1C",
            "2023W45",
            "hRQsZhmvqgS",
            "8"
        ],
        [
            "wryMP8p8k1C",
            "2023W46",
            "hRQsZhmvqgS",
            "13"
        ],
        [
            "wryMP8p8k1C",
            "2023W50",
            "RdNV4tTRNEo",
            "21"
        ],
        [
            "wryMP8p8k1C",
            "2023W52",
            "RdNV4tTRNEo",
            "23"
        ],
        [
            "wryMP8p8k1C",
            "2023W32",
            "RdNV4tTRNEo",
            "1"
        ],
        [
            "wryMP8p8k1C",
            "2023W20",
            "pFCZqWnXtoU",
            "25"
        ],
        [
            "wryMP8p8k1C",
            "2023W24",
            "pFCZqWnXtoU",
            "31"
        ],
        [
            "wryMP8p8k1C",
            "2023W43",
            "hRQsZhmvqgS",
            "8"
        ],
        [
            "wryMP8p8k1C",
            "2023W44",
            "hRQsZhmvqgS",
            "8"
        ],
        [
            "wryMP8p8k1C",
            "2023W47",
            "hRQsZhmvqgS",
            "12"
        ],
        [
            "wryMP8p8k1C",
            "2023W48",
            "hRQsZhmvqgS",
            "14"
        ],
        [
            "wryMP8p8k1C",
            "2024W14",
            "pFCZqWnXtoU",
            "33"
        ],
        [
            "wryMP8p8k1C",
            "2024W15",
            "pFCZqWnXtoU",
            "40"
        ],
        [
            "wryMP8p8k1C",
            "2023W21",
            "pFCZqWnXtoU",
            "22"
        ],
        [
            "wryMP8p8k1C",
            "2023W51",
            "RdNV4tTRNEo",
            "21"
        ],
        [
            "wryMP8p8k1C",
            "2024W10",
            "pFCZqWnXtoU",
            "52"
        ],
        [
            "wryMP8p8k1C",
            "2024W11",
            "pFCZqWnXtoU",
            "39"
        ],
        [
            "wryMP8p8k1C",
            "2024W10",
            "MBZYTqkEgwf",
            "21"
        ],
        [
            "wryMP8p8k1C",
            "2023W35",
            "TOgZ99Jv0bN",
            "1"
        ],
        [
            "wryMP8p8k1C",
            "2024W12",
            "pFCZqWnXtoU",
            "43"
        ],
        [
            "wryMP8p8k1C",
            "2024W13",
            "pFCZqWnXtoU",
            "35"
        ],
        [
            "wryMP8p8k1C",
            "2023W40",
            "hRQsZhmvqgS",
            "5"
        ],
        [
            "wryMP8p8k1C",
            "2024W12",
            "MBZYTqkEgwf",
            "18"
        ],
        [
            "wryMP8p8k1C",
            "2023W39",
            "TOgZ99Jv0bN",
            "1"
        ],
        [
            "wryMP8p8k1C",
            "2024W11",
            "MBZYTqkEgwf",
            "15"
        ],
        [
            "wryMP8p8k1C",
            "2023W21",
            "MBZYTqkEgwf",
            "12"
        ],
        [
            "wryMP8p8k1C",
            "2023W23",
            "MBZYTqkEgwf",
            "7"
        ],
        [
            "wryMP8p8k1C",
            "2024W15",
            "hdeC7uX9Cko",
            "61"
        ],
        [
            "wryMP8p8k1C",
            "2023W20",
            "MBZYTqkEgwf",
            "12"
        ],
        [
            "wryMP8p8k1C",
            "2023W24",
            "MBZYTqkEgwf",
            "9"
        ],
        [
            "wryMP8p8k1C",
            "2024W13",
            "MBZYTqkEgwf",
            "20"
        ],
        [
            "wryMP8p8k1C",
            "2024W13",
            "hdeC7uX9Cko",
            "75"
        ],
        [
            "wryMP8p8k1C",
            "2024W12",
            "dOhqCNenSjS",
            "9"
        ],
        [
            "wryMP8p8k1C",
            "2024W14",
            "MBZYTqkEgwf",
            "17"
        ],
        [
            "wryMP8p8k1C",
            "2024W12",
            "hdeC7uX9Cko",
            "75"
        ],
        [
            "wryMP8p8k1C",
            "2024W14",
            "hdeC7uX9Cko",
            "87"
        ],
        [
            "wryMP8p8k1C",
            "2024W13",
            "dOhqCNenSjS",
            "16"
        ],
        [
            "wryMP8p8k1C",
            "2024W15",
            "MBZYTqkEgwf",
            "24"
        ],
        [
            "wryMP8p8k1C",
            "2024W14",
            "dOhqCNenSjS",
            "28"
        ],
        [
            "wryMP8p8k1C",
            "2023W22",
            "MBZYTqkEgwf",
            "11"
        ],
        [
            "wryMP8p8k1C",
            "2023W50",
            "K27JzTKmBKh",
            "9"
        ],
        [
            "wryMP8p8k1C",
            "2023W29",
            "MBZYTqkEgwf",
            "11"
        ],
        [
            "wryMP8p8k1C",
            "2023W51",
            "K27JzTKmBKh",
            "12"
        ],
        [
            "wryMP8p8k1C",
            "2023W27",
            "MBZYTqkEgwf",
            "9"
        ],
        [
            "wryMP8p8k1C",
            "2023W28",
            "MBZYTqkEgwf",
            "12"
        ],
        [
            "wryMP8p8k1C",
            "2023W52",
            "K27JzTKmBKh",
            "19"
        ],
        [
            "wryMP8p8k1C",
            "2023W25",
            "MBZYTqkEgwf",
            "11"
        ],
        [
            "wryMP8p8k1C",
            "2023W49",
            "hRQsZhmvqgS",
            "10"
        ],
        [
            "wryMP8p8k1C",
            "2024W11",
            "dOhqCNenSjS",
            "9"
        ],
        [
            "wryMP8p8k1C",
            "2024W10",
            "dOhqCNenSjS",
            "6"
        ],
        [
            "wryMP8p8k1C",
            "2023W26",
            "MBZYTqkEgwf",
            "15"
        ],
        [
            "wryMP8p8k1C",
            "2024W8",
            "TOgZ99Jv0bN",
            "61"
        ],
        [
            "wryMP8p8k1C",
            "2023W49",
            "K27JzTKmBKh",
            "7"
        ],
        [
            "wryMP8p8k1C",
            "2024W4",
            "sv6c7CpPcrc",
            "25"
        ],
        [
            "wryMP8p8k1C",
            "2023W34",
            "hRQsZhmvqgS",
            "3"
        ],
        [
            "wryMP8p8k1C",
            "2024W2",
            "sv6c7CpPcrc",
            "41"
        ],
        [
            "wryMP8p8k1C",
            "2024W6",
            "sv6c7CpPcrc",
            "18"
        ],
        [
            "wryMP8p8k1C",
            "2023W47",
            "FRmrFTE63D0",
            "18"
        ],
        [
            "wryMP8p8k1C",
            "2023W30",
            "pFCZqWnXtoU",
            "5"
        ],
        [
            "wryMP8p8k1C",
            "2023W34",
            "pFCZqWnXtoU",
            "2"
        ],
        [
            "wryMP8p8k1C",
            "2024W2",
            "TOgZ99Jv0bN",
            "51"
        ],
        [
            "wryMP8p8k1C",
            "2023W47",
            "K27JzTKmBKh",
            "6"
        ],
        [
            "wryMP8p8k1C",
            "2023W45",
            "FRmrFTE63D0",
            "29"
        ],
        [
            "wryMP8p8k1C",
            "2023W32",
            "pFCZqWnXtoU",
            "2"
        ],
        [
            "wryMP8p8k1C",
            "2024W6",
            "hdeC7uX9Cko",
            "62"
        ],
        [
            "wryMP8p8k1C",
            "2024W4",
            "RdNV4tTRNEo",
            "18"
        ],
        [
            "wryMP8p8k1C",
            "2024W4",
            "hdeC7uX9Cko",
            "92"
        ],
        [
            "wryMP8p8k1C",
            "2024W2",
            "hdeC7uX9Cko",
            "94"
        ],
        [
            "wryMP8p8k1C",
            "2024W2",
            "RdNV4tTRNEo",
            "32"
        ],
        [
            "wryMP8p8k1C",
            "2023W30",
            "hRQsZhmvqgS",
            "3"
        ],
        [
            "wryMP8p8k1C",
            "2023W32",
            "hRQsZhmvqgS",
            "5"
        ],
        [
            "wryMP8p8k1C",
            "2023W19",
            "sv6c7CpPcrc",
            "1"
        ],
        [
            "wryMP8p8k1C",
            "2023W49",
            "FRmrFTE63D0",
            "36"
        ],
        [
            "wryMP8p8k1C",
            "2023W27",
            "sv6c7CpPcrc",
            "4"
        ],
        [
            "wryMP8p8k1C",
            "2023W17",
            "sv6c7CpPcrc",
            "1"
        ],
        [
            "wryMP8p8k1C",
            "2023W29",
            "sv6c7CpPcrc",
            "4"
        ],
        [
            "wryMP8p8k1C",
            "2023W51",
            "sv6c7CpPcrc",
            "40"
        ],
        [
            "wryMP8p8k1C",
            "2024W6",
            "RdNV4tTRNEo",
            "19"
        ],
        [
            "wryMP8p8k1C",
            "2023W51",
            "FRmrFTE63D0",
            "27"
        ],
        [
            "wryMP8p8k1C",
            "2023W51",
            "XKGgynPS1WZ",
            "21"
        ],
        [
            "wryMP8p8k1C",
            "2023W21",
            "sv6c7CpPcrc",
            "1"
        ],
        [
            "wryMP8p8k1C",
            "2023W51",
            "TOgZ99Jv0bN",
            "54"
        ],
        [
            "wryMP8p8k1C",
            "2023W24",
            "RdNV4tTRNEo",
            "2"
        ],
        [
            "wryMP8p8k1C",
            "2023W27",
            "pFCZqWnXtoU",
            "38"
        ],
        [
            "wryMP8p8k1C",
            "2024W4",
            "TOgZ99Jv0bN",
            "65"
        ],
        [
            "wryMP8p8k1C",
            "2024W8",
            "sv6c7CpPcrc",
            "20"
        ],
        [
            "wryMP8p8k1C",
            "2024W8",
            "RdNV4tTRNEo",
            "20"
        ],
        [
            "wryMP8p8k1C",
            "2023W25",
            "pFCZqWnXtoU",
            "34"
        ],
        [
            "wryMP8p8k1C",
            "2024W6",
            "TOgZ99Jv0bN",
            "40"
        ],
        [
            "wryMP8p8k1C",
            "2023W36",
            "pFCZqWnXtoU",
            "2"
        ],
        [
            "wryMP8p8k1C",
            "2023W46",
            "XKGgynPS1WZ",
            "25"
        ],
        [
            "wryMP8p8k1C",
            "2023W44",
            "XKGgynPS1WZ",
            "20"
        ],
        [
            "wryMP8p8k1C",
            "2023W48",
            "XKGgynPS1WZ",
            "26"
        ],
        [
            "wryMP8p8k1C",
            "2024W2",
            "MBZYTqkEgwf",
            "15"
        ],
        [
            "wryMP8p8k1C",
            "2023W34",
            "FRmrFTE63D0",
            "2"
        ],
        [
            "wryMP8p8k1C",
            "2023W29",
            "pFCZqWnXtoU",
            "9"
        ],
        [
            "wryMP8p8k1C",
            "2023W19",
            "MBZYTqkEgwf",
            "12"
        ],
        [
            "wryMP8p8k1C",
            "2023W18",
            "dOhqCNenSjS",
            "6"
        ],
        [
            "wryMP8p8k1C",
            "2024W6",
            "pFCZqWnXtoU",
            "26"
        ],
        [
            "wryMP8p8k1C",
            "2024W6",
            "MBZYTqkEgwf",
            "16"
        ],
        [
            "wryMP8p8k1C",
            "2024W8",
            "hRQsZhmvqgS",
            "17"
        ],
        [
            "wryMP8p8k1C",
            "2024W4",
            "pFCZqWnXtoU",
            "41"
        ],
        [
            "wryMP8p8k1C",
            "2024W4",
            "MBZYTqkEgwf",
            "23"
        ],
        [
            "wryMP8p8k1C",
            "2024W6",
            "hRQsZhmvqgS",
            "16"
        ],
        [
            "wryMP8p8k1C",
            "2023W32",
            "MBZYTqkEgwf",
            "13"
        ],
        [
            "wryMP8p8k1C",
            "2023W30",
            "MBZYTqkEgwf",
            "5"
        ],
        [
            "wryMP8p8k1C",
            "2023W34",
            "MBZYTqkEgwf",
            "8"
        ],
        [
            "wryMP8p8k1C",
            "2024W2",
            "pFCZqWnXtoU",
            "53"
        ],
        [
            "wryMP8p8k1C",
            "2024W5",
            "dOhqCNenSjS",
            "17"
        ],
        [
            "wryMP8p8k1C",
            "2024W9",
            "dOhqCNenSjS",
            "7"
        ],
        [
            "wryMP8p8k1C",
            "2024W8",
            "MBZYTqkEgwf",
            "30"
        ],
        [
            "wryMP8p8k1C",
            "2024W7",
            "dOhqCNenSjS",
            "13"
        ],
        [
            "wryMP8p8k1C",
            "2024W8",
            "hdeC7uX9Cko",
            "100"
        ],
        [
            "wryMP8p8k1C",
            "2023W17",
            "MBZYTqkEgwf",
            "9"
        ],
        [
            "wryMP8p8k1C",
            "2024W1",
            "dOhqCNenSjS",
            "17"
        ],
        [
            "wryMP8p8k1C",
            "2023W19",
            "hRQsZhmvqgS",
            "4"
        ],
        [
            "wryMP8p8k1C",
            "2023W36",
            "MBZYTqkEgwf",
            "4"
        ],
        [
            "wryMP8p8k1C",
            "2023W45",
            "K27JzTKmBKh",
            "13"
        ],
        [
            "wryMP8p8k1C",
            "2023W38",
            "hRQsZhmvqgS",
            "1"
        ],
        [
            "wryMP8p8k1C",
            "2023W51",
            "rO2RVJWHpCe",
            "38"
        ],
        [
            "wryMP8p8k1C",
            "2024W3",
            "dOhqCNenSjS",
            "19"
        ],
        [
            "wryMP8p8k1C",
            "2023W17",
            "hRQsZhmvqgS",
            "16"
        ],
        [
            "wryMP8p8k1C",
            "2023W28",
            "dOhqCNenSjS",
            "1"
        ],
        [
            "wryMP8p8k1C",
            "2023W28",
            "FRmrFTE63D0",
            "20"
        ],
        [
            "wryMP8p8k1C",
            "2023W29",
            "FRmrFTE63D0",
            "16"
        ],
        [
            "wryMP8p8k1C",
            "2024W15",
            "RdNV4tTRNEo",
            "21"
        ],
        [
            "wryMP8p8k1C",
            "2023W35",
            "XKGgynPS1WZ",
            "4"
        ],
        [
            "wryMP8p8k1C",
            "2024W14",
            "VWGSudnonm5",
            "47"
        ],
        [
            "wryMP8p8k1C",
            "2023W38",
            "XKGgynPS1WZ",
            "1"
        ],
        [
            "wryMP8p8k1C",
            "2024W14",
            "RdNV4tTRNEo",
            "15"
        ],
        [
            "wryMP8p8k1C",
            "2023W47",
            "rO2RVJWHpCe",
            "29"
        ],
        [
            "wryMP8p8k1C",
            "2023W27",
            "dOhqCNenSjS",
            "2"
        ],
        [
            "wryMP8p8k1C",
            "2023W49",
            "quFXhkOJGB4",
            "23"
        ],
        [
            "wryMP8p8k1C",
            "2023W24",
            "FRmrFTE63D0",
            "45"
        ],
        [
            "wryMP8p8k1C",
            "2023W25",
            "FRmrFTE63D0",
            "25"
        ],
        [
            "wryMP8p8k1C",
            "2024W11",
            "RdNV4tTRNEo",
            "24"
        ],
        [
            "wryMP8p8k1C",
            "2024W12",
            "sv6c7CpPcrc",
            "12"
        ],
        [
            "wryMP8p8k1C",
            "2023W44",
            "rO2RVJWHpCe",
            "53"
        ],
        [
            "wryMP8p8k1C",
            "2024W15",
            "VWGSudnonm5",
            "45"
        ],
        [
            "wryMP8p8k1C",
            "2023W42",
            "quFXhkOJGB4",
            "4"
        ],
        [
            "wryMP8p8k1C",
            "2024W10",
            "RdNV4tTRNEo",
            "26"
        ],
        [
            "wryMP8p8k1C",
            "2023W23",
            "dOhqCNenSjS",
            "4"
        ],
        [
            "wryMP8p8k1C",
            "2023W24",
            "dOhqCNenSjS",
            "4"
        ],
        [
            "wryMP8p8k1C",
            "2023W47",
            "W6sNfkJcXGC",
            "4"
        ],
        [
            "wryMP8p8k1C",
            "2023W39",
            "XKGgynPS1WZ",
            "4"
        ],
        [
            "wryMP8p8k1C",
            "2024W10",
            "VWGSudnonm5",
            "58"
        ],
        [
            "wryMP8p8k1C",
            "2023W48",
            "rO2RVJWHpCe",
            "44"
        ],
        [
            "wryMP8p8k1C",
            "2023W51",
            "MBZYTqkEgwf",
            "26"
        ],
        [
            "wryMP8p8k1C",
            "2023W50",
            "MBZYTqkEgwf",
            "20"
        ],
        [
            "wryMP8p8k1C",
            "2024W11",
            "VWGSudnonm5",
            "74"
        ],
        [
            "wryMP8p8k1C",
            "2023W50",
            "pFCZqWnXtoU",
            "36"
        ],
        [
            "wryMP8p8k1C",
            "2024W6",
            "FRmrFTE63D0",
            "24"
        ],
        [
            "wryMP8p8k1C",
            "2024W5",
            "FRmrFTE63D0",
            "27"
        ],
        [
            "wryMP8p8k1C",
            "2024W3",
            "hRQsZhmvqgS",
            "8"
        ],
        [
            "wryMP8p8k1C",
            "2023W52",
            "W6sNfkJcXGC",
            "9"
        ],
        [
            "wryMP8p8k1C",
            "2023W46",
            "W6sNfkJcXGC",
            "16"
        ],
        [
            "wryMP8p8k1C",
            "2024W4",
            "hRQsZhmvqgS",
            "9"
        ],
        [
            "wryMP8p8k1C",
            "2024W2",
            "FRmrFTE63D0",
            "19"
        ],
        [
            "wryMP8p8k1C",
            "2024W11",
            "YvLOmtTQD6b",
            "3"
        ],
        [
            "wryMP8p8k1C",
            "2024W1",
            "FRmrFTE63D0",
            "33"
        ],
        [
            "wryMP8p8k1C",
            "2024W9",
            "FRmrFTE63D0",
            "31"
        ],
        [
            "wryMP8p8k1C",
            "2024W10",
            "YvLOmtTQD6b",
            "10"
        ],
        [
            "wryMP8p8k1C",
            "2023W21",
            "FRmrFTE63D0",
            "26"
        ],
        [
            "wryMP8p8k1C",
            "2024W15",
            "YvLOmtTQD6b",
            "14"
        ],
        [
            "wryMP8p8k1C",
            "2023W31",
            "FRmrFTE63D0",
            "4"
        ],
        [
            "wryMP8p8k1C",
            "2023W32",
            "FRmrFTE63D0",
            "6"
        ],
        [
            "wryMP8p8k1C",
            "2023W30",
            "XKGgynPS1WZ",
            "4"
        ],
        [
            "wryMP8p8k1C",
            "2024W13",
            "sv6c7CpPcrc",
            "18"
        ],
        [
            "wryMP8p8k1C",
            "2023W31",
            "XKGgynPS1WZ",
            "6"
        ],
        [
            "wryMP8p8k1C",
            "2023W48",
            "pFCZqWnXtoU",
            "30"
        ],
        [
            "wryMP8p8k1C",
            "2024W13",
            "TOgZ99Jv0bN",
            "68"
        ],
        [
            "wryMP8p8k1C",
            "2024W14",
            "YvLOmtTQD6b",
            "3"
        ],
        [
            "wryMP8p8k1C",
            "2023W20",
            "FRmrFTE63D0",
            "19"
        ],
        [
            "wryMP8p8k1C",
            "2023W47",
            "pFCZqWnXtoU",
            "35"
        ],
        [
            "wryMP8p8k1C",
            "2024W12",
            "TOgZ99Jv0bN",
            "67"
        ],
        [
            "wryMP8p8k1C",
            "2023W44",
            "pFCZqWnXtoU",
            "34"
        ],
        [
            "wryMP8p8k1C",
            "2023W23",
            "hRQsZhmvqgS",
            "2"
        ],
        [
            "wryMP8p8k1C",
            "2023W39",
            "quFXhkOJGB4",
            "6"
        ],
        [
            "wryMP8p8k1C",
            "2023W22",
            "hRQsZhmvqgS",
            "4"
        ],
        [
            "wryMP8p8k1C",
            "2023W26",
            "hRQsZhmvqgS",
            "6"
        ],
        [
            "wryMP8p8k1C",
            "2023W17",
            "K27JzTKmBKh",
            "2"
        ],
        [
            "wryMP8p8k1C",
            "2024W12",
            "hRQsZhmvqgS",
            "13"
        ],
        [
            "wryMP8p8k1C",
            "2023W31",
            "quFXhkOJGB4",
            "7"
        ],
        [
            "wryMP8p8k1C",
            "2023W52",
            "quFXhkOJGB4",
            "19"
        ],
        [
            "wryMP8p8k1C",
            "2023W36",
            "W6sNfkJcXGC",
            "8"
        ],
        [
            "wryMP8p8k1C",
            "2023W40",
            "MBZYTqkEgwf",
            "2"
        ],
        [
            "wryMP8p8k1C",
            "2024W13",
            "hRQsZhmvqgS",
            "21"
        ],
        [
            "wryMP8p8k1C",
            "2024W3",
            "K27JzTKmBKh",
            "6"
        ],
        [
            "wryMP8p8k1C",
            "2024W7",
            "K27JzTKmBKh",
            "19"
        ],
        [
            "wryMP8p8k1C",
            "2023W48",
            "vBWtCmNNnCG",
            "30"
        ],
        [
            "wryMP8p8k1C",
            "2024W1",
            "VWGSudnonm5",
            "44"
        ],
        [
            "wryMP8p8k1C",
            "2023W47",
            "vBWtCmNNnCG",
            "19"
        ],
        [
            "wryMP8p8k1C",
            "2023W44",
            "MBZYTqkEgwf",
            "31"
        ],
        [
            "wryMP8p8k1C",
            "2023W32",
            "quFXhkOJGB4",
            "1"
        ],
        [
            "wryMP8p8k1C",
            "2024W4",
            "K27JzTKmBKh",
            "13"
        ],
        [
            "wryMP8p8k1C",
            "2023W44",
            "vBWtCmNNnCG",
            "49"
        ],
        [
            "wryMP8p8k1C",
            "2023W20",
            "dOhqCNenSjS",
            "4"
        ],
        [
            "wryMP8p8k1C",
            "2023W41",
            "dOhqCNenSjS",
            "1"
        ],
        [
            "wryMP8p8k1C",
            "2023W49",
            "hdeC7uX9Cko",
            "70"
        ],
        [
            "wryMP8p8k1C",
            "2023W35",
            "quFXhkOJGB4",
            "1"
        ],
        [
            "wryMP8p8k1C",
            "2023W46",
            "hdeC7uX9Cko",
            "42"
        ],
        [
            "wryMP8p8k1C",
            "2023W34",
            "K27JzTKmBKh",
            "1"
        ],
        [
            "wryMP8p8k1C",
            "2023W47",
            "MBZYTqkEgwf",
            "28"
        ],
        [
            "wryMP8p8k1C",
            "2023W45",
            "hdeC7uX9Cko",
            "48"
        ],
        [
            "wryMP8p8k1C",
            "2023W27",
            "hRQsZhmvqgS",
            "4"
        ],
        [
            "wryMP8p8k1C",
            "2023W48",
            "MBZYTqkEgwf",
            "36"
        ],
        [
            "wryMP8p8k1C",
            "2023W36",
            "quFXhkOJGB4",
            "1"
        ],
        [
            "wryMP8p8k1C",
            "2024W8",
            "K27JzTKmBKh",
            "13"
        ],
        [
            "wryMP8p8k1C",
            "2023W46",
            "c4HrGRJoarj",
            "27"
        ],
        [
            "wryMP8p8k1C",
            "2023W33",
            "pFCZqWnXtoU",
            "3"
        ],
        [
            "wryMP8p8k1C",
            "2023W48",
            "K27JzTKmBKh",
            "5"
        ],
        [
            "wryMP8p8k1C",
            "2023W33",
            "hRQsZhmvqgS",
            "7"
        ],
        [
            "wryMP8p8k1C",
            "2023W21",
            "RdNV4tTRNEo",
            "1"
        ],
        [
            "wryMP8p8k1C",
            "2024W1",
            "hdeC7uX9Cko",
            "92"
        ],
        [
            "wryMP8p8k1C",
            "2024W7",
            "TOgZ99Jv0bN",
            "54"
        ],
        [
            "wryMP8p8k1C",
            "2024W3",
            "sv6c7CpPcrc",
            "35"
        ],
        [
            "wryMP8p8k1C",
            "2024W7",
            "sv6c7CpPcrc",
            "39"
        ],
        [
            "wryMP8p8k1C",
            "2023W48",
            "dOhqCNenSjS",
            "5"
        ],
        [
            "wryMP8p8k1C",
            "2023W46",
            "FRmrFTE63D0",
            "26"
        ],
        [
            "wryMP8p8k1C",
            "2024W9",
            "VWGSudnonm5",
            "63"
        ],
        [
            "wryMP8p8k1C",
            "2023W40",
            "vBWtCmNNnCG",
            "1"
        ],
        [
            "wryMP8p8k1C",
            "2024W15",
            "c4HrGRJoarj",
            "33"
        ],
        [
            "wryMP8p8k1C",
            "2023W29",
            "quFXhkOJGB4",
            "9"
        ],
        [
            "wryMP8p8k1C",
            "2024W5",
            "VWGSudnonm5",
            "48"
        ],
        [
            "wryMP8p8k1C",
            "2023W29",
            "W6sNfkJcXGC",
            "1"
        ],
        [
            "wryMP8p8k1C",
            "2023W29",
            "RdNV4tTRNEo",
            "1"
        ],
        [
            "wryMP8p8k1C",
            "2024W5",
            "hdeC7uX9Cko",
            "75"
        ],
        [
            "wryMP8p8k1C",
            "2023W44",
            "dOhqCNenSjS",
            "13"
        ],
        [
            "wryMP8p8k1C",
            "2024W1",
            "RdNV4tTRNEo",
            "29"
        ],
        [
            "wryMP8p8k1C",
            "2023W25",
            "W6sNfkJcXGC",
            "6"
        ],
        [
            "wryMP8p8k1C",
            "2023W18",
            "XKGgynPS1WZ",
            "21"
        ],
        [
            "wryMP8p8k1C",
            "2024W5",
            "YvLOmtTQD6b",
            "11"
        ],
        [
            "wryMP8p8k1C",
            "2023W21",
            "W6sNfkJcXGC",
            "48"
        ],
        [
            "wryMP8p8k1C",
            "2023W32",
            "W6sNfkJcXGC",
            "2"
        ],
        [
            "wryMP8p8k1C",
            "2024W11",
            "FRmrFTE63D0",
            "33"
        ],
        [
            "wryMP8p8k1C",
            "2024W1",
            "XKGgynPS1WZ",
            "32"
        ],
        [
            "wryMP8p8k1C",
            "2024W5",
            "XKGgynPS1WZ",
            "38"
        ],
        [
            "wryMP8p8k1C",
            "2024W1",
            "YvLOmtTQD6b",
            "11"
        ],
        [
            "wryMP8p8k1C",
            "2024W9",
            "YvLOmtTQD6b",
            "8"
        ],
        [
            "wryMP8p8k1C",
            "2023W26",
            "sv6c7CpPcrc",
            "1"
        ],
        [
            "wryMP8p8k1C",
            "2024W5",
            "RdNV4tTRNEo",
            "23"
        ],
        [
            "wryMP8p8k1C",
            "2024W15",
            "FRmrFTE63D0",
            "27"
        ],
        [
            "wryMP8p8k1C",
            "2024W3",
            "TOgZ99Jv0bN",
            "52"
        ],
        [
            "wryMP8p8k1C",
            "2024W6",
            "W6sNfkJcXGC",
            "17"
        ],
        [
            "wryMP8p8k1C",
            "2024W9",
            "XKGgynPS1WZ",
            "40"
        ],
        [
            "wryMP8p8k1C",
            "2024W9",
            "RdNV4tTRNEo",
            "17"
        ],
        [
            "wryMP8p8k1C",
            "2023W26",
            "pFCZqWnXtoU",
            "34"
        ],
        [
            "wryMP8p8k1C",
            "2023W52",
            "XKGgynPS1WZ",
            "28"
        ],
        [
            "wryMP8p8k1C",
            "2023W20",
            "XKGgynPS1WZ",
            "47"
        ],
        [
            "wryMP8p8k1C",
            "2024W11",
            "c4HrGRJoarj",
            "42"
        ],
        [
            "wryMP8p8k1C",
            "2023W52",
            "FRmrFTE63D0",
            "40"
        ],
        [
            "wryMP8p8k1C",
            "2023W18",
            "FRmrFTE63D0",
            "9"
        ],
        [
            "wryMP8p8k1C",
            "2023W39",
            "FRmrFTE63D0",
            "1"
        ],
        [
            "wryMP8p8k1C",
            "2023W24",
            "XKGgynPS1WZ",
            "9"
        ],
        [
            "wryMP8p8k1C",
            "2023W17",
            "dOhqCNenSjS",
            "6"
        ],
        [
            "wryMP8p8k1C",
            "2023W45",
            "XKGgynPS1WZ",
            "30"
        ],
        [
            "wryMP8p8k1C",
            "2023W49",
            "XKGgynPS1WZ",
            "30"
        ],
        [
            "wryMP8p8k1C",
            "2023W50",
            "TOgZ99Jv0bN",
            "73"
        ],
        [
            "wryMP8p8k1C",
            "2024W2",
            "W6sNfkJcXGC",
            "13"
        ],
        [
            "wryMP8p8k1C",
            "2023W50",
            "vBWtCmNNnCG",
            "52"
        ],
        [
            "wryMP8p8k1C",
            "2024W7",
            "pFCZqWnXtoU",
            "48"
        ],
        [
            "wryMP8p8k1C",
            "2023W50",
            "sv6c7CpPcrc",
            "41"
        ],
        [
            "wryMP8p8k1C",
            "2024W7",
            "MBZYTqkEgwf",
            "25"
        ],
        [
            "wryMP8p8k1C",
            "2023W16",
            "vBWtCmNNnCG",
            "4"
        ],
        [
            "wryMP8p8k1C",
            "2023W28",
            "XKGgynPS1WZ",
            "3"
        ],
        [
            "wryMP8p8k1C",
            "2024W3",
            "pFCZqWnXtoU",
            "48"
        ],
        [
            "wryMP8p8k1C",
            "2024W3",
            "MBZYTqkEgwf",
            "25"
        ],
        [
            "wryMP8p8k1C",
            "2024W7",
            "hRQsZhmvqgS",
            "24"
        ],
        [
            "wryMP8p8k1C",
            "2023W52",
            "hdeC7uX9Cko",
            "66"
        ],
        [
            "wryMP8p8k1C",
            "2024W11",
            "quFXhkOJGB4",
            "22"
        ],
        [
            "wryMP8p8k1C",
            "2024W4",
            "dOhqCNenSjS",
            "16"
        ],
        [
            "wryMP8p8k1C",
            "2024W3",
            "rO2RVJWHpCe",
            "41"
        ],
        [
            "wryMP8p8k1C",
            "2024W7",
            "rO2RVJWHpCe",
            "32"
        ],
        [
            "wryMP8p8k1C",
            "2024W15",
            "quFXhkOJGB4",
            "14"
        ],
        [
            "wryMP8p8k1C",
            "2024W8",
            "dOhqCNenSjS",
            "8"
        ],
        [
            "wryMP8p8k1C",
            "2023W21",
            "quFXhkOJGB4",
            "15"
        ],
        [
            "wryMP8p8k1C",
            "2023W33",
            "MBZYTqkEgwf",
            "10"
        ],
        [
            "wryMP8p8k1C",
            "2023W33",
            "vBWtCmNNnCG",
            "17"
        ],
        [
            "wryMP8p8k1C",
            "2023W30",
            "dOhqCNenSjS",
            "2"
        ],
        [
            "wryMP8p8k1C",
            "2023W33",
            "rO2RVJWHpCe",
            "2"
        ],
        [
            "wryMP8p8k1C",
            "2023W50",
            "rO2RVJWHpCe",
            "38"
        ],
        [
            "wryMP8p8k1C",
            "2023W51",
            "dOhqCNenSjS",
            "6"
        ],
        [
            "wryMP8p8k1C",
            "2024W13",
            "K27JzTKmBKh",
            "25"
        ],
        [
            "wryMP8p8k1C",
            "2023W44",
            "K27JzTKmBKh",
            "12"
        ],
        [
            "wryMP8p8k1C",
            "2024W9",
            "hdeC7uX9Cko",
            "101"
        ],
        [
            "wryMP8p8k1C",
            "2023W16",
            "MBZYTqkEgwf",
            "9"
        ],
        [
            "wryMP8p8k1C",
            "2023W46",
            "quFXhkOJGB4",
            "26"
        ],
        [
            "wryMP8p8k1C",
            "2023W16",
            "hRQsZhmvqgS",
            "3"
        ],
        [
            "wryMP8p8k1C",
            "2023W25",
            "quFXhkOJGB4",
            "5"
        ],
        [
            "wryMP8p8k1C",
            "2023W37",
            "MBZYTqkEgwf",
            "3"
        ],
        [
            "wryMP8p8k1C",
            "2024W7",
            "vBWtCmNNnCG",
            "33"
        ]
    ],
    "width": 4
}